deepseek_reason_extractor/__init__.py
deepseek_reason_extractor/core.py
deepseek_reason_extractor-0.1.0.dist-info/LICENSE
deepseek_reason_extractor-0.1.0.dist-info/METADATA
deepseek_reason_extractor-0.1.0.dist-info/WHEEL
deepseek_reason_extractor-0.1.0.dist-info/top_level.txt
deepseek_reason_extractor-0.1.0.dist-info/RECORD
