Metadata-Version: 2.2
Name: deepseek_reason_extractor
Version: 0.1.0
Summary: A Python package for extracting and processing reasoning patterns
Author-email: Your Name <your.email@example.com>
Project-URL: Homepage, https://github.com/yourusername/deepseek_reason_extractor
Classifier: Programming Language :: Python :: 3
Classifier: License :: OSI Approved :: MIT License
Classifier: Operating System :: OS Independent
Requires-Python: >=3.8
License-File: LICENSE
Requires-Dist: vaklm>=0.1.0
